{"nodes": [{"id": "c_coding_web_development_next_prime_property_src_components_property_deletepropertydialog_tsx", "label": "DeletePropertyDialog.tsx", "file_type": "code", "source_file": "C:\\Coding\\Web Development\\Next\\prime-property\\src\\components\\property\\DeletePropertyDialog.tsx", "source_location": "L1"}, {"id": "property_deletepropertydialog_handleconfirm", "label": "handleConfirm()", "file_type": "code", "source_file": "C:\\Coding\\Web Development\\Next\\prime-property\\src\\components\\property\\DeletePropertyDialog.tsx", "source_location": "L30"}], "edges": [{"source": "c_coding_web_development_next_prime_property_src_components_property_deletepropertydialog_tsx", "target": "react", "relation": "imports_from", "context": "import", "confidence": "EXTRACTED", "source_file": "C:\\Coding\\Web Development\\Next\\prime-property\\src\\components\\property\\DeletePropertyDialog.tsx", "source_location": "L3", "weight": 1.0}, {"source": "c_coding_web_development_next_prime_property_src_components_property_deletepropertydialog_tsx", "target": "navigation", "relation": "imports_from", "context": "import", "confidence": "EXTRACTED", "source_file": "C:\\Coding\\Web Development\\Next\\prime-property\\src\\components\\property\\DeletePropertyDialog.tsx", "source_location": "L4", "weight": 1.0}, {"source": "c_coding_web_development_next_prime_property_src_components_property_deletepropertydialog_tsx", "target": "sonner", "relation": "imports_from", "context": "import", "confidence": "EXTRACTED", "source_file": "C:\\Coding\\Web Development\\Next\\prime-property\\src\\components\\property\\DeletePropertyDialog.tsx", "source_location": "L5", "weight": 1.0}, {"source": "c_coding_web_development_next_prime_property_src_components_property_deletepropertydialog_tsx", "target": "lucide_react", "relation": "imports_from", "context": "import", "confidence": "EXTRACTED", "source_file": "C:\\Coding\\Web Development\\Next\\prime-property\\src\\components\\property\\DeletePropertyDialog.tsx", "source_location": "L6", "weight": 1.0}, {"source": "c_coding_web_development_next_prime_property_src_components_property_deletepropertydialog_tsx", "target": "c_coding_web_development_next_prime_property_src_components_ui_button", "relation": "imports_from", "context": "import", "confidence": "EXTRACTED", "source_file": "C:\\Coding\\Web Development\\Next\\prime-property\\src\\components\\property\\DeletePropertyDialog.tsx", "source_location": "L7", "weight": 1.0}, {"source": "c_coding_web_development_next_prime_property_src_components_property_deletepropertydialog_tsx", "target": "ui_button_button", "relation": "imports", "context": "import", "confidence": "EXTRACTED", "source_file": "C:\\Coding\\Web Development\\Next\\prime-property\\src\\components\\property\\DeletePropertyDialog.tsx", "source_location": "L7", "weight": 1.0}, {"source": "c_coding_web_development_next_prime_property_src_components_property_deletepropertydialog_tsx", "target": "c_coding_web_development_next_prime_property_src_components_ui_dialog", "relation": "imports_from", "context": "import", "confidence": "EXTRACTED", "source_file": "C:\\Coding\\Web Development\\Next\\prime-property\\src\\components\\property\\DeletePropertyDialog.tsx", "source_location": "L8", "weight": 1.0}, {"source": "c_coding_web_development_next_prime_property_src_components_property_deletepropertydialog_tsx", "target": "ui_dialog_dialog", "relation": "imports", "context": "import", "confidence": "EXTRACTED", "source_file": "C:\\Coding\\Web Development\\Next\\prime-property\\src\\components\\property\\DeletePropertyDialog.tsx", "source_location": "L8", "weight": 1.0}, {"source": "c_coding_web_development_next_prime_property_src_components_property_deletepropertydialog_tsx", "target": "ui_dialog_dialogcontent", "relation": "imports", "context": "import", "confidence": "EXTRACTED", "source_file": "C:\\Coding\\Web Development\\Next\\prime-property\\src\\components\\property\\DeletePropertyDialog.tsx", "source_location": "L8", "weight": 1.0}, {"source": "c_coding_web_development_next_prime_property_src_components_property_deletepropertydialog_tsx", "target": "ui_dialog_dialogdescription", "relation": "imports", "context": "import", "confidence": "EXTRACTED", "source_file": "C:\\Coding\\Web Development\\Next\\prime-property\\src\\components\\property\\DeletePropertyDialog.tsx", "source_location": "L8", "weight": 1.0}, {"source": "c_coding_web_development_next_prime_property_src_components_property_deletepropertydialog_tsx", "target": "ui_dialog_dialogfooter", "relation": "imports", "context": "import", "confidence": "EXTRACTED", "source_file": "C:\\Coding\\Web Development\\Next\\prime-property\\src\\components\\property\\DeletePropertyDialog.tsx", "source_location": "L8", "weight": 1.0}, {"source": "c_coding_web_development_next_prime_property_src_components_property_deletepropertydialog_tsx", "target": "ui_dialog_dialogheader", "relation": "imports", "context": "import", "confidence": "EXTRACTED", "source_file": "C:\\Coding\\Web Development\\Next\\prime-property\\src\\components\\property\\DeletePropertyDialog.tsx", "source_location": "L8", "weight": 1.0}, {"source": "c_coding_web_development_next_prime_property_src_components_property_deletepropertydialog_tsx", "target": "ui_dialog_dialogtitle", "relation": "imports", "context": "import", "confidence": "EXTRACTED", "source_file": "C:\\Coding\\Web Development\\Next\\prime-property\\src\\components\\property\\DeletePropertyDialog.tsx", "source_location": "L8", "weight": 1.0}, {"source": "c_coding_web_development_next_prime_property_src_components_property_deletepropertydialog_tsx", "target": "ui_dialog_dialogtrigger", "relation": "imports", "context": "import", "confidence": "EXTRACTED", "source_file": "C:\\Coding\\Web Development\\Next\\prime-property\\src\\components\\property\\DeletePropertyDialog.tsx", "source_location": "L8", "weight": 1.0}, {"source": "c_coding_web_development_next_prime_property_src_components_property_deletepropertydialog_tsx", "target": "c_coding_web_development_next_prime_property_src_lib_actions_properties", "relation": "imports_from", "context": "import", "confidence": "EXTRACTED", "source_file": "C:\\Coding\\Web Development\\Next\\prime-property\\src\\components\\property\\DeletePropertyDialog.tsx", "source_location": "L17", "weight": 1.0}, {"source": "c_coding_web_development_next_prime_property_src_components_property_deletepropertydialog_tsx", "target": "actions_properties_deleteproperty", "relation": "imports", "context": "import", "confidence": "EXTRACTED", "source_file": "C:\\Coding\\Web Development\\Next\\prime-property\\src\\components\\property\\DeletePropertyDialog.tsx", "source_location": "L17", "weight": 1.0}, {"source": "c_coding_web_development_next_prime_property_src_components_property_deletepropertydialog_tsx", "target": "property_deletepropertydialog_handleconfirm", "relation": "contains", "confidence": "EXTRACTED", "source_file": "C:\\Coding\\Web Development\\Next\\prime-property\\src\\components\\property\\DeletePropertyDialog.tsx", "source_location": "L30", "weight": 1.0}], "raw_calls": [{"caller_nid": "property_deletepropertydialog_handleconfirm", "callee": "setLoading", "is_member_call": false, "source_file": "C:\\Coding\\Web Development\\Next\\prime-property\\src\\components\\property\\DeletePropertyDialog.tsx", "source_location": "L31"}, {"caller_nid": "property_deletepropertydialog_handleconfirm", "callee": "deleteProperty", "is_member_call": false, "source_file": "C:\\Coding\\Web Development\\Next\\prime-property\\src\\components\\property\\DeletePropertyDialog.tsx", "source_location": "L32"}, {"caller_nid": "property_deletepropertydialog_handleconfirm", "callee": "setLoading", "is_member_call": false, "source_file": "C:\\Coding\\Web Development\\Next\\prime-property\\src\\components\\property\\DeletePropertyDialog.tsx", "source_location": "L33"}, {"caller_nid": "property_deletepropertydialog_handleconfirm", "callee": "setOpen", "is_member_call": false, "source_file": "C:\\Coding\\Web Development\\Next\\prime-property\\src\\components\\property\\DeletePropertyDialog.tsx", "source_location": "L36"}, {"caller_nid": "property_deletepropertydialog_handleconfirm", "callee": "success", "is_member_call": true, "source_file": "C:\\Coding\\Web Development\\Next\\prime-property\\src\\components\\property\\DeletePropertyDialog.tsx", "source_location": "L37"}, {"caller_nid": "property_deletepropertydialog_handleconfirm", "callee": "push", "is_member_call": true, "source_file": "C:\\Coding\\Web Development\\Next\\prime-property\\src\\components\\property\\DeletePropertyDialog.tsx", "source_location": "L38"}, {"caller_nid": "property_deletepropertydialog_handleconfirm", "callee": "error", "is_member_call": true, "source_file": "C:\\Coding\\Web Development\\Next\\prime-property\\src\\components\\property\\DeletePropertyDialog.tsx", "source_location": "L40"}]}